parsextract/__init__.py
parsextract/constants.py
parsextract/parser.py
parsextract-0.1.10.dist-info/LICENSE
parsextract-0.1.10.dist-info/METADATA
parsextract-0.1.10.dist-info/WHEEL
parsextract-0.1.10.dist-info/top_level.txt
parsextract-0.1.10.dist-info/RECORD
