Metadata-Version: 2.2
Name: parsextract
Version: 0.1.10
Summary: A library to extract IPs, domains, and emails from text
Home-page: https://github.com/deepakkumar/parsextract
Author: Deepak Kumar
Author-email: deepak.kumar@cyware.com
Classifier: Programming Language :: Python :: 3
Classifier: License :: OSI Approved :: MIT License
Classifier: Operating System :: OS Independent
Requires-Python: >=3.6
License-File: LICENSE
Dynamic: author
Dynamic: author-email
Dynamic: classifier
Dynamic: description
Dynamic: description-content-type
Dynamic: home-page
Dynamic: requires-python
Dynamic: summary
